health_ml/__init__.py
health_ml/deep_learning_config.py
health_ml/eval_runner.py
health_ml/experiment_config.py
health_ml/lightning_container.py
health_ml/model_trainer.py
health_ml/runner.py
health_ml/runner_base.py
health_ml/training_runner.py
health_ml/configs/hello_world.py
health_ml/data/__init__.py
health_ml/losses/__init__.py
health_ml/networks/__init__.py
health_ml/networks/blocks/__init__.py
health_ml/networks/layers/__init__.py
health_ml/networks/layers/attention_layers.py
health_ml/networks/nets/__init__.py
health_ml/utils/__init__.py
health_ml/utils/bag_utils.py
health_ml/utils/box_utils.py
health_ml/utils/checkpoint_handler.py
health_ml/utils/checkpoint_utils.py
health_ml/utils/common_utils.py
health_ml/utils/config_loader.py
health_ml/utils/data_augmentations.py
health_ml/utils/diagnostics.py
health_ml/utils/fixed_paths.py
health_ml/utils/lightning_loggers.py
health_ml/utils/logging.py
health_ml/utils/lr_scheduler.py
health_ml/utils/model_util.py
health_ml/utils/package_setup.py
health_ml/utils/regression_test_utils.py
health_ml/utils/reports.py
health_ml/utils/serialization.py
health_ml/utils/split_dataset.py
health_ml/utils/type_annotations.py
hi_ml-0.5.4.dist-info/LICENSE
hi_ml-0.5.4.dist-info/METADATA
hi_ml-0.5.4.dist-info/WHEEL
hi_ml-0.5.4.dist-info/entry_points.txt
hi_ml-0.5.4.dist-info/top_level.txt
hi_ml-0.5.4.dist-info/RECORD
